conf_man/__init__.py
conf_man/conf_man.py
test/__init__.py
test/test_conf_man/__init__.py
test/test_conf_man/test_conf_man.py
confmanager-0.0.3.dist-info/LICENSE
confmanager-0.0.3.dist-info/METADATA
confmanager-0.0.3.dist-info/WHEEL
confmanager-0.0.3.dist-info/top_level.txt
confmanager-0.0.3.dist-info/RECORD
