Metadata-Version: 2.1
Name: confmanager
Version: 0.0.3
Summary: Assist in parsing cli options and parameters
Home-page: https://github.com/haogooder666/conf_man
Author: Haogooder
Author-email: haogooder@163.com
License: MIT
Platform: UNKNOWN
Classifier: Programming Language :: Python :: 3
Classifier: License :: OSI Approved :: MIT License
Classifier: Operating System :: OS Independent
Requires-Python: >=3
Requires-Dist: pyyaml
